exoplanet_atlas
